WGM_api/__init__.py
WGM_api/wgm.py
wgm_api-0.1.19.dist-info/METADATA
wgm_api-0.1.19.dist-info/WHEEL
wgm_api-0.1.19.dist-info/RECORD
