Metadata-Version: 2.1
Name: WGM_api
Version: 0.1.19
Summary: A Python client library for managing WireGuard server users and sessions.
Author: Andrey Ivanov
Author-email: andrey.ivanov.dev13@gmail.com
Requires-Python: >=3.10,<4.0
Classifier: Programming Language :: Python :: 3
Classifier: Programming Language :: Python :: 3.10
Classifier: Programming Language :: Python :: 3.11
Classifier: Programming Language :: Python :: 3.12
Classifier: Programming Language :: Python :: 3.13
Requires-Dist: autopep8 (>=2.3.1,<3.0.0)
Requires-Dist: flake8 (>=7.1.1,<8.0.0)
Requires-Dist: requests (>=2.32.3,<3.0.0)
